pylanguage/__init__.py
pylanguage/translator.py
pylanguage-0.1.0.dist-info/METADATA
pylanguage-0.1.0.dist-info/WHEEL
pylanguage-0.1.0.dist-info/licenses/LICENSE
pylanguage-0.1.0.dist-info/RECORD
