Metadata-Version: 2.3
Name: pylanguage
Version: 0.1.0
Summary: Translation assistant for Python
Project-URL: Homepage, https://github.com/aerocyber/pylanguage
Project-URL: Issues, https://github.com/aerocyber/pylanguage/issues
Author-email: Aero <aerocyberdev@proton.me>
License-File: LICENSE
Classifier: License :: OSI Approved :: MIT License
Classifier: Operating System :: OS Independent
Classifier: Programming Language :: Python :: 3
Requires-Python: >=3.8
